redlock_plus.py
redlock_plus-0.1.6.dist-info/LICENSE
redlock_plus-0.1.6.dist-info/WHEEL
redlock_plus-0.1.6.dist-info/METADATA
redlock_plus-0.1.6.dist-info/RECORD
