Metadata-Version: 2.1
Name: redlock-plus
Version: 0.1.6
Summary: Distributed locks with Redis
Home-page: https://github.com/provinzkraut/redlock-plus
License: MIT
Keywords: redlock,redis,lock,distributed
Author: Janek Nouvertné
Author-email: provinzkraut@posteo.de
Requires-Python: >=3.7
Classifier: Development Status :: 5 - Production/Stable
Classifier: Intended Audience :: Developers
Classifier: License :: OSI Approved :: MIT License
Classifier: Programming Language :: Python :: 3
Classifier: Programming Language :: Python :: 3.7
Classifier: Programming Language :: Python :: 3.8
Classifier: Programming Language :: Python :: 3.9
Classifier: Programming Language :: Python :: 3.10
Classifier: Programming Language :: Python :: 3.10
Classifier: Programming Language :: Python :: 3.7
Classifier: Programming Language :: Python :: 3.8
Classifier: Programming Language :: Python :: 3.9
Classifier: Programming Language :: Python :: Implementation :: CPython
Classifier: Programming Language :: Python :: Implementation :: PyPy
Provides-Extra: docs
Requires-Dist: Sphinx (>=4.3.1,<5.0.0); extra == "docs"
Requires-Dist: importlib-metadata (<4.3); python_version < "3.8"
Requires-Dist: redis (>=4.0.2,<5.0.0)
Requires-Dist: sphinx-autodoc-typehints (>=1.12.0,<2.0.0); (platform_python_implementation == "CPython") and (extra == "docs")
Project-URL: Documentation, https://redlock-plus.readthedocs.io/en/latest/
Project-URL: Repository, https://github.com/provinzkraut/redlock-plus
